setup.py
pymac/__init__.py
pymac/pymac.py
pymac.egg-info/PKG-INFO
pymac.egg-info/SOURCES.txt
pymac.egg-info/dependency_links.txt
pymac.egg-info/entry_points.txt
pymac.egg-info/top_level.txt