Metadata-Version: 1.0
Name: pymac
Version: 1.0.0
Summary: PyMac 1.0.0 [Python MAC Adress Changer]
Home-page: UNKNOWN
Author: BrainDisassembly
Author-email: braindisassm@gmail.com
License: GPL v3
Platform: UNKNOWN
